.gitignore
.travis.yml
AUTHORS
ChangeLog
LICENSE
MANIFEST.in
README.rst
TODO
appveyor.yml
build-manylinux-wheels.sh
build_inplace
dev-requirements.txt
make-manylinux
setup.cfg
setup.py
setup_libuv.py
tasks.py
tox.ini
.travis/before_install.sh
appveyor/install.ps1
appveyor/run_with_env.cmd
deps/libuv/include/android-ifaddrs.h
deps/libuv/include/pthread-barrier.h
deps/libuv/include/stdint-msvc2008.h
deps/libuv/include/tree.h
deps/libuv/include/uv-aix.h
deps/libuv/include/uv-bsd.h
deps/libuv/include/uv-darwin.h
deps/libuv/include/uv-errno.h
deps/libuv/include/uv-linux.h
deps/libuv/include/uv-os390.h
deps/libuv/include/uv-posix.h
deps/libuv/include/uv-sunos.h
deps/libuv/include/uv-threadpool.h
deps/libuv/include/uv-unix.h
deps/libuv/include/uv-version.h
deps/libuv/include/uv-win.h
deps/libuv/include/uv.h
deps/libuv/src/fs-poll.c
deps/libuv/src/heap-inl.h
deps/libuv/src/inet.c
deps/libuv/src/queue.h
deps/libuv/src/threadpool.c
deps/libuv/src/uv-common.c
deps/libuv/src/uv-common.h
deps/libuv/src/version.c
deps/libuv/src/unix/aix.c
deps/libuv/src/unix/android-ifaddrs.c
deps/libuv/src/unix/async.c
deps/libuv/src/unix/atomic-ops.h
deps/libuv/src/unix/bsd-ifaddrs.c
deps/libuv/src/unix/core.c
deps/libuv/src/unix/cygwin.c
deps/libuv/src/unix/darwin-proctitle.c
deps/libuv/src/unix/darwin.c
deps/libuv/src/unix/dl.c
deps/libuv/src/unix/freebsd.c
deps/libuv/src/unix/fs.c
deps/libuv/src/unix/fsevents.c
deps/libuv/src/unix/getaddrinfo.c
deps/libuv/src/unix/getnameinfo.c
deps/libuv/src/unix/internal.h
deps/libuv/src/unix/kqueue.c
deps/libuv/src/unix/linux-core.c
deps/libuv/src/unix/linux-inotify.c
deps/libuv/src/unix/linux-syscalls.c
deps/libuv/src/unix/linux-syscalls.h
deps/libuv/src/unix/loop-watcher.c
deps/libuv/src/unix/loop.c
deps/libuv/src/unix/netbsd.c
deps/libuv/src/unix/no-fsevents.c
deps/libuv/src/unix/no-proctitle.c
deps/libuv/src/unix/openbsd.c
deps/libuv/src/unix/os390-syscalls.c
deps/libuv/src/unix/os390-syscalls.h
deps/libuv/src/unix/os390.c
deps/libuv/src/unix/pipe.c
pyuv_kathara.egg-info/PKG-INFO
pyuv_kathara.egg-info/SOURCES.txt
pyuv_kathara.egg-info/dependency_links.txt
pyuv_kathara.egg-info/top_level.txt
